tik_tak_toe_mcp/__init__.py
tik_tak_toe_mcp/__main__.py
tik_tak_toe_mcp/game_state.json
tik_tak_toe_mcp/server.py
tik_tak_toe_mcp/tik-tak-toe-mcp.log
tik_tak_toe_mcp/ui/__init__.py
tik_tak_toe_mcp-0.1.0.dist-info/METADATA
tik_tak_toe_mcp-0.1.0.dist-info/WHEEL
tik_tak_toe_mcp-0.1.0.dist-info/entry_points.txt
tik_tak_toe_mcp-0.1.0.dist-info/RECORD
