Metadata-Version: 2.4
Name: tik-tak-toe-mcp
Version: 0.1.0
Summary: Tic-Tac-Toe MCP Server with separate UI
Requires-Python: >=3.10
Requires-Dist: mcp[cli]>=1.2.0
